{
  "product_slug": "meeting-cost-calculator",
  "generated_at": "2026-03-08T17:41:37.647Z",
  "primary_keyword": "meeting cost calculator",
  "secondary_keywords": [
    "web app",
    "Teams and small businesses",
    "tool",
    "app"
  ],
  "meta_title": "Meeting Cost Calculator – SaaS tool that estimates the cost ",
  "meta_description": "SaaS tool that estimates the cost of meetings by duration and attendees for teams.",
  "seo_headings": {
    "h1": "Meeting Cost Calculator",
    "h2": [
      "SaaS tool that estimates the cost of meetings by duration an",
      "Features",
      "How it works",
      "Get started"
    ]
  }
}